[{"id": 3572887, "name": "Commonwealth of The Bahamas", "country": "BS", "coord": [25.040819, -77.371223]}, {"id": 3571815, "name": "New Providence District", "country": "BS", "coord": [25.033331, -77.283333]}, {"id": 3571824, "name": "Nassau", "country": "BS", "coord": [25.058229, -77.343063]}, {"id": 3572374, "name": "City of Freeport District", "country": "BS", "coord": [26.520281, -78.645279]}, {"id": 3572375, "name": "Freeport", "country": "BS", "coord": [26.533331, -78.699997]}, {"id": 3571912, "name": "Marsh Harbour District", "country": "BS", "coord": [26.4, -77.166672]}, {"id": 3571913, "name": "Marsh Harbour", "country": "BS", "coord": [26.541241, -77.063599]}, {"id": 8030559, "name": "West Grand Bahama District", "country": "BS", "coord": [26.59333, -78.600563]}, {"id": 3571224, "name": "West End", "country": "BS", "coord": [26.683331, -78.966667]}, {"id": 8030555, "name": "South Abaco District", "country": "BS", "coord": [26.04694, -77.243607]}, {"id": 3571500, "name": "Sandy Point", "country": "BS", "coord": [26.01667, -77.400002]}, {"id": 3572154, "name": "Inagua District", "country": "BS", "coord": [21.076941, -73.311668]}, {"id": 3571898, "name": "Matthew Town", "country": "BS", "coord": [20.950001, -73.666672]}, {"id": 3571493, "name": "San Salvador District", "country": "BS", "coord": [24.036671, -74.493057]}, {"id": 3571264, "name": "Victoria Hill", "country": "BS", "coord": [24.08333, -74.51667]}, {"id": 3571964, "name": "Macbride", "country": "BS", "coord": [25.066669, -77.466667]}, {"id": 8030546, "name": "East Grand Bahama District", "country": "BS", "coord": [26.671671, -78.141388]}, {"id": 3572333, "name": "Golden Grove", "country": "BS", "coord": [26.6, -78.333328]}, {"id": 8030557, "name": "South Eleuthera District", "country": "BS", "coord": [24.800831, -76.18306]}, {"id": 3830951, "name": "Kemps Point", "country": "BS", "coord": [24.906389, -76.183327]}, {"id": 8030553, "name": "North Eleuthera District", "country": "BS", "coord": [25.46278, -76.67556]}, {"id": 3571275, "name": "Upper Bogue", "country": "BS", "coord": [25.450001, -76.666672]}, {"id": 3572807, "name": "Bimini District", "country": "BS", "coord": [25.704439, -79.288887]}, {"id": 3572924, "name": "Alice Town", "country": "BS", "coord": [25.716669, -79.300003]}, {"id": 8030556, "name": "South Andros District", "country": "BS", "coord": [23.923611, -77.648888]}, {"id": 3572603, "name": "Congo Town", "country": "BS", "coord": [24.16667, -77.583328]}, {"id": 8030552, "name": "North Andros District", "country": "BS", "coord": [24.766939, -78.096107]}, {"id": 3571865, "name": "Minns", "country": "BS", "coord": [24.700001, -77.76667]}, {"id": 3571971, "name": "Lucaya", "country": "BS", "coord": [26.533331, -78.666672]}, {"id": 3571592, "name": "Rock Sound", "country": "BS", "coord": [24.9, -76.199997]}, {"id": 8030554, "name": "Rum Cay District", "country": "BS", "coord": [23.678061, -74.856667]}, {"id": 3571650, "name": "Port Nelson", "country": "BS", "coord": [23.633329, -74.833328]}, {"id": 3572189, "name": "High Rock", "country": "BS", "coord": [26.620831, -78.283333]}, {"id": 8030550, "name": "Moore\u2019s Island District", "country": "BS", "coord": [26.300831, -77.554169]}, {"id": 3572233, "name": "Hard Bargain", "country": "BS", "coord": [26.316669, -77.566673]}, {"id": 3572462, "name": "Dunmore Town", "country": "BS", "coord": [25.5, -76.650002]}, {"id": 8030551, "name": "North Abaco District", "country": "BS", "coord": [26.78944, -77.436943]}, {"id": 3572601, "name": "Coopers Town", "country": "BS", "coord": [26.866671, -77.51667]}, {"id": 8030545, "name": "Crooked Island and Long Cay District", "country": "BS", "coord": [22.73361, -74.215279]}, {"id": 3572620, "name": "Colonel Hill", "country": "BS", "coord": [22.76667, -74.216667]}, {"id": 3572627, "name": "Cockburn Town", "country": "BS", "coord": [24.033331, -74.51667]}, {"id": 3572005, "name": "Long Island District", "country": "BS", "coord": [23.216669, -75.111671]}, {"id": 3572640, "name": "Clarence Town", "country": "BS", "coord": [23.1, -74.98333]}, {"id": 3572906, "name": "Andros Town", "country": "BS", "coord": [24.700001, -77.76667]}]