[{"id": 3574116, "name": "Mon Repos", "country": "TT", "coord": [10.283, -61.446049]}, {"id": 3575052, "name": "Arima", "country": "TT", "coord": [10.63333, -61.283329]}, {"id": 3574888, "name": "Canaan", "country": "TT", "coord": [10.25, -61.466671]}, {"id": 7521943, "name": "Point Fortin", "country": "TT", "coord": [10.184, -61.681969]}, {"id": 3573899, "name": "Point Fortin", "country": "TT", "coord": [10.18333, -61.683331]}, {"id": 7521937, "name": "Chaguanas", "country": "TT", "coord": [10.51718, -61.415031]}, {"id": 3573591, "name": "Republic of Trinidad and Tobago", "country": "TT", "coord": [11, -61]}, {"id": 3573650, "name": "Tabaquite", "country": "TT", "coord": [10.38333, -61.299999]}, {"id": 3573804, "name": "Saint Andrew", "country": "TT", "coord": [10.41667, -61.466671]}, {"id": 3574345, "name": "La Finette", "country": "TT", "coord": [10.73333, -61.51667]}, {"id": 3573606, "name": "Tobago", "country": "TT", "coord": [11.25, -60.666672]}, {"id": 3573520, "name": "Woodlands", "country": "TT", "coord": [11.24973, -60.722618]}, {"id": 3573768, "name": "Saint Margaret", "country": "TT", "coord": [10.33333, -61.450001]}, {"id": 3573891, "name": "City of Port of Spain", "country": "TT", "coord": [10.65, -61.51667]}, {"id": 3574738, "name": "Corbeaux Town", "country": "TT", "coord": [10.65, -61.51667]}, {"id": 3573773, "name": "Saint Joseph", "country": "TT", "coord": [10.65, -61.416672]}, {"id": 3574211, "name": "Manahambre", "country": "TT", "coord": [10.26667, -61.383331]}, {"id": 3574578, "name": "Exchange", "country": "TT", "coord": [10.41667, -61.450001]}, {"id": 3574604, "name": "El Dorado", "country": "TT", "coord": [10.63333, -61.383331]}, {"id": 3574794, "name": "Chase Village", "country": "TT", "coord": [10.46667, -61.416672]}, {"id": 3573989, "name": "Paradise", "country": "TT", "coord": [10.65, -61.366669]}, {"id": 3573643, "name": "Paradise", "country": "TT", "coord": [10.63471, -61.366711]}, {"id": 3574081, "name": "Morvant", "country": "TT", "coord": [10.65, -61.466671]}, {"id": 3573703, "name": "Scarborough", "country": "TT", "coord": [11.18333, -60.73333]}, {"id": 3574524, "name": "Gasparillo", "country": "TT", "coord": [10.31667, -61.416672]}, {"id": 7521945, "name": "Siparia", "country": "TT", "coord": [10.13382, -61.501209]}, {"id": 3573681, "name": "Siparia", "country": "TT", "coord": [10.13333, -61.5]}, {"id": 3573652, "name": "Success", "country": "TT", "coord": [10.65, -61.48333]}, {"id": 7521939, "name": "Diego Martin", "country": "TT", "coord": [10.7005, -61.534168]}, {"id": 3573935, "name": "Petit Valley", "country": "TT", "coord": [10.7, -61.533329]}, {"id": 3574878, "name": "Cantaro", "country": "TT", "coord": [10.7, -61.466671]}, {"id": 3574184, "name": "Maraval", "country": "TT", "coord": [10.7, -61.51667]}, {"id": 3573957, "name": "Petit Bourg", "country": "TT", "coord": [10.65, -61.450001]}, {"id": 7521941, "name": "Penal/Debe", "country": "TT", "coord": [10.16778, -61.46524]}, {"id": 3573965, "name": "Penal", "country": "TT", "coord": [10.16667, -61.466671]}, {"id": 3574536, "name": "Fyzabad", "country": "TT", "coord": [10.18333, -61.549999]}, {"id": 3574773, "name": "Claxton Bay", "country": "TT", "coord": [10.35, -61.466671]}, {"id": 3574671, "name": "Curepe", "country": "TT", "coord": [10.63333, -61.400002]}, {"id": 3573854, "name": "Red Hill", "country": "TT", "coord": [10.61667, -61.316669]}, {"id": 3574632, "name": "Dinsley", "country": "TT", "coord": [10.63333, -61.349998]}, {"id": 3573781, "name": "Saint Helena", "country": "TT", "coord": [10.58333, -61.333328]}, {"id": 3573764, "name": "Saint Marys", "country": "TT", "coord": [10.45, -61.416672]}, {"id": 3574104, "name": "Moriah", "country": "TT", "coord": [11.24606, -60.71365]}, {"id": 3574038, "name": "New Grant", "country": "TT", "coord": [10.28333, -61.316669]}, {"id": 3573885, "name": "Preysal", "country": "TT", "coord": [10.41667, -61.400002]}, {"id": 3573995, "name": "Palo Seco", "country": "TT", "coord": [10.08333, -61.583328]}, {"id": 3574806, "name": "Chaguaramas", "country": "TT", "coord": [10.68333, -61.633331]}, {"id": 3574957, "name": "Boissiere Village", "country": "TT", "coord": [10.66667, -61.51667]}, {"id": 3574323, "name": "La Pastora", "country": "TT", "coord": [10.71667, -61.466671]}, {"id": 3573541, "name": "Waterloo", "country": "TT", "coord": [10.46667, -61.466671]}, {"id": 7521940, "name": "Eastern Tobago", "country": "TT", "coord": [11.24988, -60.58419]}, {"id": 3573819, "name": "Roxborough", "country": "TT", "coord": [11.25, -60.583328]}, {"id": 3573604, "name": "Toco", "country": "TT", "coord": [10.83333, -60.950001]}, {"id": 3573972, "name": "Patience Hill", "country": "TT", "coord": [11.18822, -60.763889]}, {"id": 3573645, "name": "Tableland", "country": "TT", "coord": [10.26667, -61.26667]}, {"id": 3573596, "name": "Tortuga", "country": "TT", "coord": [10.36667, -61.400002]}, {"id": 3574952, "name": "Bon Accord Village", "country": "TT", "coord": [11.1543, -60.83075]}, {"id": 3574689, "name": "Cumuto", "country": "TT", "coord": [10.58333, -61.200001]}, {"id": 3574497, "name": "Gran Couva", "country": "TT", "coord": [10.4, -61.366669]}, {"id": 3574877, "name": "Caparo", "country": "TT", "coord": [10.45, -61.333328]}, {"id": 3574087, "name": "Moruga", "country": "TT", "coord": [10.08333, -61.283329]}, {"id": 3574168, "name": "Matura", "country": "TT", "coord": [10.66667, -61.066669]}, {"id": 3573638, "name": "Talparo", "country": "TT", "coord": [10.5, -61.26667]}, {"id": 3573850, "name": "Reform", "country": "TT", "coord": [10.3, -61.416672]}, {"id": 3574552, "name": "Four Roads", "country": "TT", "coord": [10.68639, -61.555]}, {"id": 3574729, "name": "Coryal", "country": "TT", "coord": [10.5, -61.183331]}, {"id": 3573918, "name": "Piparo", "country": "TT", "coord": [10.33333, -61.333328]}, {"id": 3573665, "name": "Speyside", "country": "TT", "coord": [11.29694, -60.537949]}, {"id": 3574517, "name": "Glamorgan", "country": "TT", "coord": [11.22264, -60.60984]}, {"id": 3573822, "name": "Roussillac", "country": "TT", "coord": [10.21667, -61.583328]}, {"id": 3574928, "name": "Brickfield", "country": "TT", "coord": [10.48333, -61.466671]}, {"id": 3574263, "name": "Lopinot", "country": "TT", "coord": [10.68333, -61.316669]}, {"id": 3574655, "name": "Delaford", "country": "TT", "coord": [11.26601, -60.559319]}, {"id": 3574103, "name": "Morichal", "country": "TT", "coord": [10.36035, -61.35075]}, {"id": 3575073, "name": "Adelphi", "country": "TT", "coord": [11.20969, -60.717731]}, {"id": 3574874, "name": "Cap-de-Ville", "country": "TT", "coord": [10.15, -61.700001]}, {"id": 3574986, "name": "Black Rock", "country": "TT", "coord": [11.20598, -60.781898]}, {"id": 7521947, "name": "Tunapuna/Piarco", "country": "TT", "coord": [10.63387, -61.381821]}, {"id": 3573576, "name": "Tunapuna", "country": "TT", "coord": [10.63333, -61.383331]}, {"id": 7521944, "name": "Sangre Grande", "country": "TT", "coord": [10.5835, -61.117722]}, {"id": 3573732, "name": "Sangre Grande", "country": "TT", "coord": [10.58333, -61.116669]}, {"id": 3573739, "name": "San Fernando", "country": "TT", "coord": [10.28333, -61.466671]}, {"id": 3573738, "name": "San Fernando", "country": "TT", "coord": [10.28333, -61.466671]}, {"id": 3573890, "name": "Port-of-Spain", "country": "TT", "coord": [10.66617, -61.516571]}, {"id": 3574194, "name": "Marabella", "country": "TT", "coord": [10.30618, -61.446709]}, {"id": 3574810, "name": "Chaguanas", "country": "TT", "coord": [10.51667, -61.416672]}, {"id": 3575051, "name": "Arima", "country": "TT", "coord": [10.63333, -61.283329]}, {"id": 3573840, "name": "Rio Claro", "country": "TT", "coord": [10.3, -61.183331]}, {"id": 3573882, "name": "Princes Town", "country": "TT", "coord": [10.26667, -61.383331]}, {"id": 3574069, "name": "Mucurapo", "country": "TT", "coord": [10.66667, -61.533329]}, {"id": 3574309, "name": "Laventille", "country": "TT", "coord": [10.64917, -61.49889]}, {"id": 3574659, "name": "Debe", "country": "TT", "coord": [10.2, -61.450001]}, {"id": 3574724, "name": "Couva", "country": "TT", "coord": [10.42248, -61.46748]}, {"id": 3575039, "name": "Arouca", "country": "TT", "coord": [10.63333, -61.333328]}, {"id": 3574766, "name": "Coco", "country": "TT", "coord": [10.68333, -61.583328]}, {"id": 3573794, "name": "Saint Clair", "country": "TT", "coord": [10.67039, -61.521679]}, {"id": 3574466, "name": "Green Hill", "country": "TT", "coord": [10.73333, -61.566669]}]